errfix/__init__.py
errfix/errfix.py
errfix-0.2.dist-info/METADATA
errfix-0.2.dist-info/WHEEL
errfix-0.2.dist-info/top_level.txt
errfix-0.2.dist-info/RECORD
