Metadata-Version: 2.4
Name: ErrFix
Version: 0.2
Summary: Pakiet do diagnozowania i weryfikacji błędów w Pythonie
Author: Nequ_0
Author-email: xcyber0@o2.pl
Classifier: Programming Language :: Python :: 3
Classifier: License :: OSI Approved :: MIT License
Classifier: Operating System :: OS Independent
Requires-Python: >=3.7
Dynamic: author
Dynamic: author-email
Dynamic: classifier
Dynamic: description
Dynamic: description-content-type
Dynamic: requires-python
Dynamic: summary
